{"results_returned":1,"results_start":1,"events":[{"event":{"event_id":13328,"title":"★★　中止　★★　紀里谷和明ワークショップ in 東京","event_url":"http://atnd.org/events/13328","limit":51,"accepted":51,"waiting":17,"updated_at":"2011-03-13T17:50:57.000+09:00","users":[{"user":{"user_id":56203,"nickname":"pillowh","twitter_id":"pillowh","status":1}},{"user":{"user_id":45921,"nickname":"minerva","twitter_id":"minerva_photo","status":1}},{"user":{"user_id":64327,"nickname":"Sophie","twitter_id":"sophie0113","status":1}},{"user":{"user_id":64403,"nickname":"Yoshida mami","twitter_id":"mamiyoshida","status":1}},{"user":{"user_id":64500,"nickname":"satorutokito","twitter_id":"Satoru_Tokito","status":1}},{"user":{"user_id":64507,"nickname":"笹川 拓真","twitter_id":"takmajp","status":1}},{"user":{"user_id":8390,"nickname":"mutuki","twitter_id":"mutuki","status":1}},{"user":{"user_id":64688,"nickname":"agaaga0405","twitter_id":"agaaga0405","status":1}},{"user":{"user_id":64718,"nickname":"suganoshota","twitter_id":null,"status":1}},{"user":{"user_id":64721,"nickname":"matsumaru","twitter_id":null,"status":1}},{"user":{"user_id":64730,"nickname":"masakoi","twitter_id":null,"status":1}},{"user":{"user_id":64890,"nickname":"miya315","twitter_id":null,"status":1}},{"user":{"user_id":64891,"nickname":"kyn","twitter_id":null,"status":1}},{"user":{"user_id":64894,"nickname":"h1rok1","twitter_id":null,"status":1}},{"user":{"user_id":45914,"nickname":"miyazawaten","twitter_id":"SoftJin_MiyaTen","status":1}},{"user":{"user_id":57681,"nickname":"joker7615","twitter_id":"joker7615","status":1}},{"user":{"user_id":47830,"nickname":"mare1983","twitter_id":"mare1983","status":1}},{"user":{"user_id":64916,"nickname":"neoselene","twitter_id":"Neoselene","status":1}},{"user":{"user_id":64943,"nickname":"amn130","twitter_id":"amncolorado","status":1}},{"user":{"user_id":64945,"nickname":"hiroto527","twitter_id":null,"status":1}},{"user":{"user_id":64946,"nickname":"boruzzi","twitter_id":null,"status":1}},{"user":{"user_id":45810,"nickname":"zamapark1982","twitter_id":"zamapark","status":1}},{"user":{"user_id":64948,"nickname":"nobuko","twitter_id":"sometimes_good","status":1}},{"user":{"user_id":64949,"nickname":"伊藤英","twitter_id":"crazyshen","status":1}},{"user":{"user_id":64955,"nickname":"NUT2","twitter_id":"nut2info","status":1}},{"user":{"user_id":64956,"nickname":"tiptosepia","twitter_id":"tiptosepia","status":1}},{"user":{"user_id":64964,"nickname":"MTD","twitter_id":"Mt_Drive","status":1}},{"user":{"user_id":64968,"nickname":"YAMATOspirits","twitter_id":"YAMATOspirits","status":1}},{"user":{"user_id":64972,"nickname":"gen tanaka","twitter_id":null,"status":1}},{"user":{"user_id":64977,"nickname":"achaka","twitter_id":"todays0special","status":1}},{"user":{"user_id":56195,"nickname":"butterflizm","twitter_id":"butterflizm","status":1}},{"user":{"user_id":64993,"nickname":"SHUNJI UEDA","twitter_id":null,"status":1}},{"user":{"user_id":64998,"nickname":"シャルズ君","twitter_id":null,"status":1}},{"user":{"user_id":65013,"nickname":"mfeelsogood","twitter_id":"mfeelsogood","status":1}},{"user":{"user_id":46415,"nickname":"jubilee","twitter_id":"jubilee0","status":1}},{"user":{"user_id":65034,"nickname":"imu","twitter_id":"hotcake23","status":1}},{"user":{"user_id":65050,"nickname":"しゅ。","twitter_id":"live_cinema","status":1}},{"user":{"user_id":65055,"nickname":"marikko","twitter_id":null,"status":1}},{"user":{"user_id":57876,"nickname":"green","twitter_id":null,"status":1}},{"user":{"user_id":65068,"nickname":"hatabou","twitter_id":"hatanaka_kazu","status":1}},{"user":{"user_id":57791,"nickname":"pillow","twitter_id":"nak__aji_m_a","status":1}},{"user":{"user_id":65074,"nickname":"yassy117","twitter_id":null,"status":1}},{"user":{"user_id":65078,"nickname":"skata","twitter_id":null,"status":1}},{"user":{"user_id":65077,"nickname":"siisan","twitter_id":null,"status":1}},{"user":{"user_id":47734,"nickname":"amourchef","twitter_id":"amourchef","status":1}},{"user":{"user_id":65079,"nickname":"subeteok2005","twitter_id":null,"status":1}},{"user":{"user_id":47496,"nickname":"CINEMAP_WEB","twitter_id":"CINEMAP_WEB","status":1}},{"user":{"user_id":65096,"nickname":"YUSUKEMAN","twitter_id":"YUSUKEMANIAC","status":1}},{"user":{"user_id":65093,"nickname":"akiyama_yu","twitter_id":"yucan_a","status":1}},{"user":{"user_id":65097,"nickname":"rtibigon1977","twitter_id":null,"status":1}},{"user":{"user_id":65112,"nickname":"minimie","twitter_id":"meeeay","status":1}},{"user":{"user_id":65129,"nickname":"makiiiii28","twitter_id":"makiiiii28","status":0}},{"user":{"user_id":65132,"nickname":"papipupepokksan","twitter_id":"Papipupepokksan","status":0}},{"user":{"user_id":46182,"nickname":"西村知美","twitter_id":"momicosme","status":0}},{"user":{"user_id":65233,"nickname":"_Erminea","twitter_id":"_Erminea","status":0}},{"user":{"user_id":65239,"nickname":"TABO","twitter_id":"TABO180","status":0}},{"user":{"user_id":46261,"nickname":"yukko104","twitter_id":null,"status":0}},{"user":{"user_id":56198,"nickname":"平野大輔","twitter_id":"daisuke_hirano","status":0}},{"user":{"user_id":65324,"nickname":"樹-tatsuki-","twitter_id":null,"status":0}},{"user":{"user_id":65330,"nickname":"Kochangall","twitter_id":"Kochangall","status":0}},{"user":{"user_id":65433,"nickname":"bugu","twitter_id":null,"status":0}},{"user":{"user_id":65448,"nickname":"ケイタ","twitter_id":"y333mt","status":0}},{"user":{"user_id":65465,"nickname":"hiccup","twitter_id":null,"status":0}},{"user":{"user_id":65510,"nickname":"hiromisami","twitter_id":null,"status":0}},{"user":{"user_id":65605,"nickname":"naco","twitter_id":null,"status":0}},{"user":{"user_id":65631,"nickname":"sayaka.s","twitter_id":null,"status":0}},{"user":{"user_id":65630,"nickname":"y73","twitter_id":null,"status":0}},{"user":{"user_id":65765,"nickname":"genkiPro","twitter_id":"genkiPro","status":0}}]}}]}