{"results_returned":1,"results_start":1,"events":[{"event":{"event_id":15105,"title":"第0回 AWS User Group - Japan【鹿児島】 勉強会","event_url":"http://atnd.org/events/15105","limit":21,"accepted":16,"waiting":0,"updated_at":"2011-06-12T22:52:58.000+09:00","users":[{"user":{"user_id":44875,"nickname":"Ken Tamagawa","twitter_id":"KenTamagawa","status":1}},{"user":{"user_id":71333,"nickname":"Guma-","twitter_id":null,"status":1}},{"user":{"user_id":67499,"nickname":"genta0406","twitter_id":"genta0406","status":1}},{"user":{"user_id":67502,"nickname":"ushisan","twitter_id":"ushibondi","status":1}},{"user":{"user_id":51346,"nickname":"ueue","twitter_id":null,"status":1}},{"user":{"user_id":73280,"nickname":"前原 秀己","twitter_id":"DemiiMaeha","status":1}},{"user":{"user_id":73289,"nickname":"bb56","twitter_id":null,"status":1}},{"user":{"user_id":73402,"nickname":"ka_ke","twitter_id":null,"status":1}},{"user":{"user_id":73413,"nickname":"r.shimizu","twitter_id":null,"status":1}},{"user":{"user_id":74661,"nickname":"volleyballer_kg","twitter_id":null,"status":1}},{"user":{"user_id":39450,"nickname":"zuckey","twitter_id":"zuckey3","status":1}},{"user":{"user_id":39693,"nickname":"chaba_","twitter_id":"chaba_","status":1}},{"user":{"user_id":21376,"nickname":"odaken","twitter_id":null,"status":1}},{"user":{"user_id":70132,"nickname":"tsukada","twitter_id":null,"status":1}},{"user":{"user_id":77765,"nickname":"bluesky","twitter_id":null,"status":1}},{"user":{"user_id":62523,"nickname":"佐伯真哉","twitter_id":null,"status":1}}]}}]}