{"results_returned":1,"results_start":1,"events":[{"event":{"event_id":23946,"title":"プロペラブ会　多分第1回","event_url":"http://atnd.org/events/23946","limit":10,"accepted":7,"waiting":0,"updated_at":"2012-01-13T09:52:44.000+09:00","users":[{"user":{"user_id":83941,"nickname":"す～。","twitter_id":"ksksue","status":1}},{"user":{"user_id":40095,"nickname":"K.M.A.G.","twitter_id":"kama_AGE","status":1}},{"user":{"user_id":85467,"nickname":"caskaz","twitter_id":null,"status":1}},{"user":{"user_id":51929,"nickname":"titoi2t","twitter_id":"titoi2","status":1}},{"user":{"user_id":34810,"nickname":"yishi","twitter_id":"yishii","status":1}},{"user":{"user_id":2554,"nickname":"catsin","twitter_id":"catsin","status":1}},{"user":{"user_id":14296,"nickname":"shirowarabe","twitter_id":null,"status":1}}]}}]}