{"results_returned":1,"results_start":1,"events":[{"event":{"event_id":66769,"title":"第78回InfoTalk IoTサービスプラットフォーム「SensorCorpus」を活用したIoTへの取り組み ","event_url":"http://atnd.org/events/66769","limit":30,"accepted":22,"waiting":0,"updated_at":"2015-06-01T13:57:28.000+09:00","users":[{"user":{"user_id":201198,"nickname":"mura_aiit","twitter_id":null,"status":1}},{"user":{"user_id":211972,"nickname":"shukonpei","twitter_id":null,"status":1}},{"user":{"user_id":13534,"nickname":"zhgchn","twitter_id":null,"status":1}},{"user":{"user_id":204860,"nickname":"Makt","twitter_id":null,"status":1}},{"user":{"user_id":212392,"nickname":"Yasuyuki SHIRAI","twitter_id":null,"status":1}},{"user":{"user_id":148031,"nickname":"hdb12","twitter_id":"hdb12","status":1}},{"user":{"user_id":63987,"nickname":"fortunan","twitter_id":"fortunan","status":1}},{"user":{"user_id":45315,"nickname":"ymnxx","twitter_id":"ymnxx","status":1}},{"user":{"user_id":213063,"nickname":"t.anakin","twitter_id":null,"status":1}},{"user":{"user_id":213169,"nickname":"Koichi.Kobayashi","twitter_id":null,"status":1}},{"user":{"user_id":205653,"nickname":"kawayama","twitter_id":"tomozo16","status":1}},{"user":{"user_id":213622,"nickname":"chiangmai48","twitter_id":null,"status":1}},{"user":{"user_id":22679,"nickname":"altima","twitter_id":null,"status":1}},{"user":{"user_id":201984,"nickname":"Armatus","twitter_id":"ArmatusGladii","status":1}},{"user":{"user_id":196751,"nickname":"Tatsunori Michael Ishii","twitter_id":null,"status":1}},{"user":{"user_id":4370,"nickname":"いささか先生","twitter_id":null,"status":1}},{"user":{"user_id":214047,"nickname":"yumim","twitter_id":null,"status":1}},{"user":{"user_id":124371,"nickname":"T.Okada","twitter_id":"okada_t","status":1}},{"user":{"user_id":196848,"nickname":"hukki_bou1213","twitter_id":null,"status":1}},{"user":{"user_id":203183,"nickname":"lightrail","twitter_id":"trmwy","status":1}},{"user":{"user_id":214137,"nickname":"pra_amon_not","twitter_id":null,"status":1}},{"user":{"user_id":55493,"nickname":"yukio_saitoh","twitter_id":"yukio_saitoh","status":1}}]}}]}