{"results_returned":1,"results_start":1,"events":[{"event":{"event_id":68949,"title":"melocy 真夏のファンミーティング","event_url":"http://atnd.org/events/68949","limit":5,"accepted":5,"waiting":0,"updated_at":"2015-08-05T17:07:51.000+09:00","users":[{"user":{"user_id":214666,"nickname":"Koki Murai","twitter_id":"koki1218423","status":1}},{"user":{"user_id":219563,"nickname":"sakka saka","twitter_id":"8a2OVfJjh0AqiHV","status":1}},{"user":{"user_id":214665,"nickname":"えれな","twitter_id":"ElenaTakasina","status":1}},{"user":{"user_id":219571,"nickname":"あゆ@歩夢","twitter_id":"Aym_yua","status":1}},{"user":{"user_id":219572,"nickname":"nako。","twitter_id":"rain04nayu","status":1}}]}}]}