{"results_returned":1,"results_start":1,"events":[{"event":{"event_id":95958,"title":"ヘッドショット（Yフィールド）でサバゲ会","event_url":"http://atnd.org/events/95958","limit":40,"accepted":10,"waiting":0,"updated_at":"2018-04-04T07:33:50.000+09:00","users":[{"user":{"user_id":99167,"nickname":"けろよん","twitter_id":"keroyon_","status":1}},{"user":{"user_id":141866,"nickname":"りょう　","twitter_id":"racing914","status":1}},{"user":{"user_id":308315,"nickname":"テッセ","twitter_id":"Grayman_006","status":1}},{"user":{"user_id":167970,"nickname":"アサウラ","twitter_id":"asaura_seizon","status":1}},{"user":{"user_id":163392,"nickname":"EL2","twitter_id":"elni0202","status":1}},{"user":{"user_id":189863,"nickname":"さとりん","twitter_id":"satorin_MiKi","status":1}},{"user":{"user_id":241233,"nickname":"ゴトー・メイソン","twitter_id":"GTO_Mason2","status":1}},{"user":{"user_id":309008,"nickname":"山猫@","twitter_id":"521Minoru","status":1}},{"user":{"user_id":309054,"nickname":"hase1830","twitter_id":"hase1830","status":1}},{"user":{"user_id":157861,"nickname":"祐樹_Snyeh","twitter_id":"Snyeh","status":1}}]}}]}