{"results_returned":1,"results_start":1,"events":[{"event":{"event_id":104344,"title":"【【福岡県大野城市】ママサポ☆ハッピーフェスタ～おとがっこ広場～＠イオン乙金ショッピングセンター","catch":null,"description":"\u003cp\u003e★*☆*★*☆*★*☆*★*☆*★*☆*★*☆*★*\u003cbr /\u003e\n　地域の親子出会いの広場\u003cbr /\u003e\n『OTOGACCO-おとがっこ広場-』へGO！！\u003cbr /\u003e\n★*☆*★*☆*★*☆*★*☆*★*☆*★*☆*★*\u003c/p\u003e\n\u003cp\u003e大野城市やその周辺で子育てをしている親子の出会いの広場が毎月イオン乙金ショッピングセンター内で毎月開催されます！\u003cbr /\u003e\n10時から14時半まで広場オープン中は入退場自由です♪\u003c/p\u003e\n\u003cp\u003e今回のおとがっこ広場は、AsMama認定共助サポーターママサポによるハッピーがいっぱい詰まったフェスタとなって開催します♪\u003cbr /\u003e\n体験や学び、子育て中のママ同士の交流などができる企画盛りだくさん！\u003cbr /\u003e\nワークショップブースやハイハイレースもあるのでお楽しみに♪\u003c/p\u003e\n\u003cp\u003e＜開催予定内容はこちら＞\u003cbr /\u003e\n■ハイハイレース・・・参加賞＆賞状プレゼント！\u003cbr /\u003e\n　　　　　　　　　　　※参加される方は開始5分前には受付を済ませてください。\u003cbr /\u003e\n■手形アート制作・・・お子さまの成長記念におすすめ♡\u003cbr /\u003e\n■整体師のお身体の悩み個別相談会・・・産後のお悩み、小顔、肩こり、腰痛などホームケアをアドバイス！(1人5〜10分目安。受付順にご案内します。)\u003cbr /\u003e\n■コットンパール風ピアス＆イヤリング ワークショップ・・・ピアス10組、イヤリング10組のいずれか。事前予約優先となります。\u003cbr /\u003e\n■お下がり交換会・・・サイズアウトしお洋服もシェアしませんか？参加はもらうだけでもOK！\u003cbr /\u003e\n■歯の相談タイム・・・イオン乙金SC内スマイル歯科の歯科衛生士さんにお子さま、ママの歯のことを相談できます。\u003c/p\u003e\n\u003cp\u003eand more・・・！\u003cbr /\u003e\n詳細はイベントページにて随時更新中！\u003c/p\u003e\n\u003cp\u003e※おとがっこタイムは開始時間10分前から受付となります。開始時間までには会場へお越しいただきますようお願いいたします。\u003c/p\u003e\n\u003cp\u003e・。*・。*・。*・。*・。*・。*・。*・。*・。*・。*・。*・。*・。*・\u003cbr /\u003e\n★詳細・お申し込みはこちらからどうぞ★\u003cbr /\u003e\nhttps://kosodate-share.asmama.jp/events/7901\u003c/p\u003e","event_url":"http://atnd.org/events/104344","started_at":"2019-03-20T10:00:00.000+09:00","ended_at":"2019-03-20T14:30:00.000+09:00","url":"https://kosodate-share.asmama.jp/events/7901","limit":null,"address":"福岡県 大野城市乙金 3-24-1","place":"イオン乙金店ショッピングセンター　南街区イベント広場","lat":"33.5437176","lon":"130.4973059","owner_id":278320,"owner_nickname":"うさライオン","owner_twitter_id":null,"accepted":0,"waiting":0,"updated_at":"2019-02-24T20:11:59.000+09:00"}}]}