{"results_returned":1,"results_start":1,"events":[{"event":{"event_id":22909,"title":"Force.com Advent Calendar 2011","catch":"躊躇してはいけない。いますぐ参加するんだ！","description":"\u003cp\u003e今年も Advent Calendar の季節がやってきました。\u003cbr /\u003e\n(はじめて知りました！)\u003c/p\u003e\n\u003cp\u003e12月1日からはじめるとネタが持ちそうにないので、19日(1週間前)あたりから始めたいと思います。もちろん人数が集まるようなら前倒しで！ぜひ、みんなでブログを更新しましょう。\u003c/p\u003e\n\u003cp\u003eForce.comといえば、セールスフォース・ドットコム社のプラットフォーム限定のごく一部の人が利用する言語です。その制約から技術者泣かせで、自由度のなさから嫌いな人もいるでしょう。しかし、だからこそ可愛くなってくることも！\u003c/p\u003e\n\u003cp\u003eForce.comのTipsでもいいし、ライブラリの使い方(あったっけ？)でもいい、自作のツールの紹介など、Force.comに関していれば何でも構いません。ぜひこの機会に、ブログ書きましょう。\u003c/p\u003e\n\u003cp\u003eブログ持っていない、という人もいるので、公開ははてなブログあたりに新アカウントを取っちゃおうかな、と企んでいます。\u003c/p\u003e\n\u003cp\u003e\u003cstrong\u003eクリスマスを過ぎたとしても全然 OK。正月を過ぎてしまっても、全然かまいません。補欠になっている方もぜひブログ書いてください！！\u003c/strong\u003e\u003c/p\u003e\n\u003cp\u003e最後になりましたが、ごめんなさい、Java Advent Calendarさんの紹介が素晴らしかったんでパクりましたorz\u003c/p\u003e\n\u003ch2\u003eカレンダー\u003c/h2\u003e\n\u003ctable\u003e\n\u003ctr\u003e\n\u003cth\u003e日\u003c/th\u003e\n\u003cth\u003eタイトル\u003c/th\u003e\n\u003cth\u003e執筆者\u003c/th\u003e\n\u003ctd\u003e掲載\u003c/td\u003e\n\u003c/tr\u003e\n\u003ctr\u003e\n\u003ctd\u003e1\u003c/td\u003e\n\u003ctd\u003e\u003ca href=\"http://d.hatena.ne.jp/i_love_forcecom/20111201\"\u003eForce.com勉強会の立ち上げ\u003c/a\u003e\u003c/td\u003e\n\u003ctd\u003e\u003ca href=\"http://twitter.com/#!/a_kuratani\"\u003ea-kura\u003c/a\u003e\u003c/td\u003e\n\u003ctd\u003e◯\u003c/td\u003e\n\u003c/tr\u003e\n\u003ctr\u003e\n\u003ctd\u003e2\u003c/td\u003e\n\u003ctd\u003e\u003ca href=\"http://blogjp.sforce.com/2011/12/forcecom-advent-b447.html\"\u003eForce.com Advent Calendarに参加しましょう!!\u003c/a\u003e\u003c/td\u003e\n\u003ctd\u003e\u003ca href=\"http://twitter.com/#!/mitsuhiro\"\u003emitsuhiro\u003c/a\u003e\u003c/td\u003e\n\u003ctd\u003e◯\u003c/td\u003e\n\u003c/tr\u003e\n\u003ctr\u003e\n\u003ctd\u003e3\u003c/td\u003e\n\u003ctd\u003e\u003c/td\u003e\n\u003ctd\u003e\u003c/td\u003e\n\u003ctd\u003e\u003c/td\u003e\n\u003c/tr\u003e\n\u003ctr\u003e\n\u003ctd\u003e4\u003c/td\u003e\n\u003ctd\u003e\u003c/td\u003e\n\u003ctd\u003e\u003c/td\u003e\n\u003ctd\u003e\u003c/td\u003e\n\u003c/tr\u003e\n\u003ctr\u003e\n\u003ctd\u003e5\u003c/td\u003e\n\u003ctd\u003e\u003ca href=\"http://blogjp.sforce.com/2011/12/william-a234.html\"\u003ewill.i.amによるチャリティーイベント \u0026#8211; Club Recovery\u003c/a\u003e\u003c/td\u003e\n\u003ctd\u003e\u003ca href=\"http://twitter.com/#!/mitsuhiro\"\u003emitsuhiro\u003c/a\u003e\u003c/td\u003e\n\u003ctd\u003e◯\u003c/td\u003e\n\u003c/tr\u003e\n\u003ctr\u003e\n\u003ctd\u003e6\u003c/td\u003e\n\u003ctd\u003e\u003ca href=\"http://d.hatena.ne.jp/shinichitomita/20111206/1323169892\"\u003e[salesforce][force.com][javascript] Force.com ブックマークレット\u003c/a\u003e\u003c/td\u003e\n\u003ctd\u003e\u003ca href=\"http://twitter.com/#!/stomita\"\u003estomita\u003c/a\u003e\u003c/td\u003e\n\u003ctd\u003e◯\u003c/td\u003e\n\u003c/tr\u003e\n\u003ctr\u003e\n\u003ctd\u003e7\u003c/td\u003e\n\u003ctd\u003e\u003ca href=\"http://d.hatena.ne.jp/yonet77/20111207/1323232267\"\u003eForce.comでのJSON Support\u003c/a\u003e\u003c/td\u003e\n\u003ctd\u003e\u003ca href=\"http://twitter.com/#!/yonet77\"\u003eyonet77\u003c/a\u003e\u003c/td\u003e\n\u003ctd\u003e◯\u003c/td\u003e\n\u003c/tr\u003e\n\u003ctr\u003e\n\u003ctd\u003e8\u003c/td\u003e\n\u003ctd\u003e\u003ca href=\"http://pomu0325.blogspot.com/2011/12/titanium-salesforce-modulesalesforce.html\"\u003eTitanium Salesforce module(SalesForce Toolkit for Appcelerator)の使い方\u003c/a\u003e\u003c/td\u003e\n\u003ctd\u003e\u003ca href=\"http://twitter.com/#!/pomu0325\"\u003epomu0325\u003c/a\u003e\u003c/td\u003e\n\u003ctd\u003e◯\u003c/td\u003e\n\u003c/tr\u003e\n\u003ctr\u003e\n\u003ctd\u003e9\u003c/td\u003e\n\u003ctd\u003e\u003ca href=\"http://d.hatena.ne.jp/a-kura/20111209\"\u003e[Force.com] Force.comスマートエンジニア～賢太郎の場合～\u003c/a\u003e\u003c/td\u003e\n\u003ctd\u003e\u003ca href=\"http://twitter.com/#!/a_kuratani\"\u003ea-kura\u003c/a\u003e\u003c/td\u003e\n\u003ctd\u003e◯\u003c/td\u003e\n\u003c/tr\u003e\n\u003ctr\u003e\n\u003ctd\u003e10\u003c/td\u003e\n\u003ctd\u003e\u003ca href=\"http://d.hatena.ne.jp/ksudie/20111210/1323479033\"\u003edatabase.comでいこうよ♪\u003c/a\u003e\u003c/td\u003e\n\u003ctd\u003e\u003ca href=\"http://twitter.com/#!/ksudie\"\u003eksudie\u003c/a\u003e\u003c/td\u003e\n\u003ctd\u003e◯\u003c/td\u003e\n\u003c/tr\u003e\n\u003ctr\u003e\n\u003ctd\u003e11\u003c/td\u003e\n\u003ctd\u003e\u003ca href=\"http://blogjp.sforce.com/2011/12/developer-lab-443f.html\"\u003e新しい開発者向けワークブックが公開されました！Developer Labでお待ちしてます！！\u003c/a\u003e\u003c/td\u003e\n\u003ctd\u003e\u003ca href=\"http://twitter.com/#!/m_fukahori\"\u003eMado_fuka\u003c/a\u003e\u003c/td\u003e\n\u003ctd\u003e◯\u003c/td\u003e\n\u003c/tr\u003e\n\u003ctr\u003e\n\u003ctd\u003e12\u003c/td\u003e\n\u003ctd\u003e\u003ca href=\"http://d.hatena.ne.jp/mihoko_az/20111212\"\u003e[salesforce][Force.com]チーム開発環境\u003c/a\u003e\u003c/td\u003e\n\u003ctd\u003e\u003ca href=\"http://twitter.com/#!/mihoko_az\"\u003emihoko_az\u003c/a\u003e\u003c/td\u003e\n\u003ctd\u003e◯\u003c/td\u003e\n\u003c/tr\u003e\n\u003ctr\u003e\n\u003ctd\u003e13\u003c/td\u003e\n\u003ctd\u003e\u003ca href=\"http://jiwashin.blogspot.com/2011/12/flashpdf.html\"\u003eFlashでPDF\u003c/a\u003e\u003c/td\u003e\n\u003ctd\u003e\u003ca href=\"http://twitter.com/#!/TareObjects\"\u003eTareObjects\u003c/a\u003e\u003c/td\u003e\n\u003ctd\u003e◯\u003c/td\u003e\n\u003c/tr\u003e\n\u003ctr\u003e\n\u003ctd\u003e14\u003c/td\u003e\n\u003ctd\u003e\u003ca href=\"http://blog.livedoor.jp/minoaw/archives/5491515.html\"\u003e[Salesforce]開発者コンソール用非公開API、ApexCSIAPI\u003c/a\u003e\u003c/td\u003e\n\u003ctd\u003e\u003ca href=\"http://twitter.com/#!/mino0123\"\u003eminoaw\u003c/a\u003e\u003c/td\u003e\n\u003ctd\u003e◯\u003c/td\u003e\n\u003c/tr\u003e\n\u003ctr\u003e\n\u003ctd\u003e15\u003c/td\u003e\n\u003ctd\u003e\u003ca href=\"http://blog.mokamoto.com/2011/12/cloud9idenodejs-databasecomheroku.html\"\u003eCloud9IDEでNode.js \u0026amp; Database.comのサンプルをHerokuにデプロイ\u003c/a\u003e\u003c/td\u003e\n\u003ctd\u003e\u003ca href=\"http://twitter.com/#!/mitsuhiro\"\u003emitsuhiro\u003c/a\u003e\u003c/td\u003e\n\u003ctd\u003e◯\u003c/td\u003e\n\u003c/tr\u003e\n\u003ctr\u003e\n\u003ctd\u003e16\u003c/td\u003e\n\u003ctd\u003e\u003ca href=\"http://d.hatena.ne.jp/yonet77/20111218/1324161845\"\u003eForce.comでのJSON Support ーApexコントローラのRemoteActionを添えてー\u003c/a\u003e\u003c/td\u003e\n\u003ctd\u003e\u003ca href=\"http://twitter.com/#!/yonet77\"\u003eyonet77\u003c/a\u003e\u003c/td\u003e\n\u003ctd\u003e◯\u003c/td\u003e\n\u003c/tr\u003e\n\u003ctr\u003e\n\u003ctd\u003e17\u003c/td\u003e\n\u003ctd\u003e\u003ca href=\"http://pomu0325.blogspot.com/2011/12/titanium-salesforce-modulesalesforce_18.html\"\u003eTitanium Salesforce module(SalesForce Toolkit for Appcelerator)の使い方 (2) \u003c/a\u003e\u003c/td\u003e\n\u003ctd\u003e\u003ca href=\"http://twitter.com/#!/pomu0325\"\u003epomu0325\u003c/a\u003e\u003c/td\u003e\n\u003ctd\u003e◯\u003c/td\u003e\n\u003c/tr\u003e\n\u003ctr\u003e\n\u003ctd\u003e18\u003c/td\u003e\n\u003ctd\u003e\u003ca href=\"http://d.hatena.ne.jp/a-kura/20111218\"\u003e[Force.com] Force.comスマートエンジニア～賢太郎とあすみの場合～\u003c/a\u003e\u003c/td\u003e\n\u003ctd\u003e\u003ca href=\"http://twitter.com/#!/a_kuratani\"\u003ea-kura\u003c/a\u003e\u003c/td\u003e\n\u003ctd\u003e◯\u003c/td\u003e\n\u003c/tr\u003e\n\u003ctr\u003e\n\u003ctd\u003e19\u003c/td\u003e\n\u003ctd\u003e\u003ca href=\"http://d.hatena.ne.jp/ksudie/20111219/1324253351\"\u003e[Force.com] .Net + database.comでいこうよ♪\u003c/a\u003e\u003c/td\u003e\n\u003ctd\u003e\u003ca href=\"http://twitter.com/#!/ksudie\"\u003eksudie\u003c/a\u003e\u003c/td\u003e\n\u003ctd\u003e◯\u003c/td\u003e\n\u003c/tr\u003e\n\u003ctr\u003e\n\u003ctd\u003e20\u003c/td\u003e\n\u003ctd\u003e\u003ca href=\"http://d.hatena.ne.jp/shinichitomita/20111219/1324310625\"\u003e[node.js][javascript][salesforce] Node.js からSalesforceを使う\u003c/a\u003e\u003c/td\u003e\n\u003ctd\u003e\u003ca href=\"http://twitter.com/#!/shinichitomita\"\u003eshinichitomita\u003c/a\u003e\u003c/td\u003e\n\u003ctd\u003e◯\u003c/td\u003e\n\u003c/tr\u003e\n\u003ctr\u003e\n\u003ctd\u003e21\u003c/td\u003e\n\u003ctd\u003e\u003ca href=\"http://d.hatena.ne.jp/madokafukahori/20111222/1324538557\"\u003eForce.com Flowを使ったウィザード画面開発\u003c/a\u003e\u003c/td\u003e\n\u003ctd\u003e\u003ca href=\"http://twitter.com/#!/m_fukahori\"\u003eMado_fuka\u003c/a\u003e\u003c/td\u003e\n\u003ctd\u003e◯\u003c/td\u003e\n\u003c/tr\u003e\n\u003ctr\u003e\n\u003ctd\u003e22\u003c/td\u003e\n\u003ctd\u003e\u003ca href=\"http://d.hatena.ne.jp/mihoko_az/20111222\"\u003e[salesforce][force.com]Force.com内でテストを定期実行する\u003c/a\u003e\u003c/td\u003e\n\u003ctd\u003e\u003ca href=\"http://twitter.com/#!/mihoko_az\"\u003emihoko_az\u003c/a\u003e\u003c/td\u003e\n\u003ctd\u003e◯\u003c/td\u003e\n\u003c/tr\u003e\n\u003ctr\u003e\n\u003ctd\u003e23\u003c/td\u003e\n\u003ctd\u003e\u003ca href=\"http://jiwashin.blogspot.com/2011/12/flashpdf_17.html\"\u003eFlashでPDF・続き\u003c/a\u003e\u003c/td\u003e\n\u003ctd\u003e\u003ca href=\"http://twitter.com/#!/TareObjects\"\u003eTareObjects\u003c/a\u003e\u003c/td\u003e\n\u003ctd\u003e◯\u003c/td\u003e\n\u003c/tr\u003e\n\u003ctr\u003e\n\u003ctd\u003e24\u003c/td\u003e\n\u003ctd\u003e\u003ca href=\"http://blog.livedoor.jp/minoaw/archives/5582954.html\"\u003eApex \u003cspan class=\"caps\"\u003eREST\u003c/span\u003e\u003c/a\u003e\u003c/td\u003e\n\u003ctd\u003e\u003ca href=\"http://twitter.com/#!/mino0123\"\u003eminoaw\u003c/a\u003e\u003c/td\u003e\n\u003ctd\u003e◯\u003c/td\u003e\n\u003c/tr\u003e\n\u003ctr\u003e\n\u003ctd\u003e25\u003c/td\u003e\n\u003ctd\u003e\u003ca href=\"http://blog.mokamoto.com/2011/12/forcecom.html\"\u003eChatterやコンテンツへのファイル添付を禁止するには\u003c/a\u003e\u003c/td\u003e\n\u003ctd\u003e\u003ca href=\"http://twitter.com/#!/mitsuhiro\"\u003emitsuhiro\u003c/a\u003e\u003c/td\u003e\n\u003ctd\u003e◯\u003c/td\u003e\n\u003c/tr\u003e\n\u003ctr\u003e\n\u003ctd\u003e26\u003c/td\u003e\n\u003ctd\u003e\u003ca href=\"http://junju5174.blogspot.com/2011/12/ocrsalesforcescansnap.html\"\u003e名刺ファイリングOCRのSalesforce連携（ScanSnapについてくるアレ）\u003c/a\u003e\u003c/td\u003e\n\u003ctd\u003e\u003ca href=\"http://twitter.com/#!/\"junju\u003ejunju\u003c/a\u003e\u003c/td\u003e\n\u003ctd\u003e◯\u003c/td\u003e\n\u003c/tr\u003e\n\u003ctr\u003e\n\u003ctd\u003e27\u003c/td\u003e\n\u003ctd\u003e\u003c/td\u003e\n\u003ctd\u003epiarra\u003c/td\u003e\n\u003ctd\u003e？\u003c/td\u003e\n\u003c/tr\u003e\n\u003ctr\u003e\n\u003ctd\u003e28\u003c/td\u003e\n\u003ctd\u003e\u003ca href=\"http://www.digitalcoast.co.jp/staff_blog/2011/12/1740\"\u003eForce.comライブコーディング\u003c/a\u003e\u003c/td\u003e\n\u003ctd\u003e\u003ca href=\"http://twitter.com/#!/a_kuratani\"\u003ea-kura\u003c/a\u003e\u003c/td\u003e\n\u003ctd\u003e◯\u003c/td\u003e\n\u003c/tr\u003e\n\u003ctr\u003e\n\u003ctd\u003e29\u003c/td\u003e\n\u003ctd\u003e\u003c/td\u003e\n\u003ctd\u003e\u003c/td\u003e\n\u003ctd\u003e\u003c/td\u003e\n\u003c/tr\u003e\n\u003ctr\u003e\n\u003ctd\u003e30\u003c/td\u003e\n\u003ctd\u003e\u003c/td\u003e\n\u003ctd\u003e\u003c/td\u003e\n\u003ctd\u003e\u003c/td\u003e\n\u003c/tr\u003e\n\u003ctr\u003e\n\u003ctd\u003e31\u003c/td\u003e\n\u003ctd\u003e\u003ca href=\"http://jiwashin.blogspot.com/2011/12/salesforce-mobile-sdkga.html\"\u003eSalesforce mobile SDK正式版(GA)\u003c/a\u003e\u003c/td\u003e\n\u003ctd\u003e\u003ca href=\"http://twitter.com/#!/TareObjects\"\u003eTareObjects\u003c/a\u003e\u003c/td\u003e\n\u003ctd\u003e◯\u003c/td\u003e\n\u003c/tr\u003e\n\u003c/table\u003e","event_url":"http://atnd.org/events/22909","started_at":"2011-12-16T00:00:00.000+09:00","ended_at":"2011-12-25T23:59:00.000+09:00","url":"https://www.facebook.com/groups/234943236617295/","limit":15,"address":"","place":"","lat":null,"lon":null,"owner_id":94095,"owner_nickname":"a-kura","owner_twitter_id":"a_kuratani","accepted":12,"waiting":0,"updated_at":"2012-10-29T10:35:42.000+09:00"}}]}