{"results_returned":1,"results_start":1,"events":[{"event":{"event_id":2294,"title":"Tokyo GTUG Night#5 埼玉サテライト","catch":"","description":"\u003cp\u003e12/9にGoogleオフィスで開催されるTokyo \u003cspan class=\"caps\"\u003eGTUG\u003c/span\u003e Night#5 ですが、\u003cbr /\u003e\n埼玉の大宮でもサテライト中継イベントを同時開催いたします。\u003c/p\u003e\n\u003cp\u003e\u003cb\u003eタイムテーブル:\u003c/b\u003e\u003cbr /\u003e\n\u003cb\u003e18:30- 受付開始\u003c/b\u003e\u003cbr /\u003e\n\u003cb\u003e19:00-19:10 ご挨拶／お知らせ\u003c/b\u003e\u003cbr /\u003e\n\u003cbr /\u003e\u003cbr /\u003e\n\u003cb\u003e19:10-20:10 白石俊平さん(HTML5 Google \u003cspan class=\"caps\"\u003eAPI\u003c/span\u003e Expert) による Tech Talk\u003c/b\u003e\u003cbr /\u003e\n　\u003cb\u003eタイトル: HTML5＆関連API総まくり\u003c/b\u003e\u003cbr /\u003e\n　\u003cb\u003e内容:\u003c/b\u003e PDFにして650Pを超えるHTML5仕様、さらには増え続ける関連API、そして最新動向・・・だなんて全部追ってられないよ！と言う方のために、HTML5のエッセンスをわかりやすく説明します。スライド資料は完全書き下ろし。\u003cbr /\u003e\n\u003cbr /\u003e\u003cbr /\u003e\n\u003cb\u003e20:10-21:00 Lightning Talks\u003c/b\u003e\u003cbr /\u003e\n　埼玉側でもLightning Talk の登壇者を募集します。\u003cbr /\u003e\n登壇ご希望の方は \u003ca href=\"mailto:kojiran@gmail.com\"\u003ekojiran@gmail.com\u003c/a\u003e までご連絡ください。\u003cbr /\u003e\nテーマは Google Technology に関連していればなんでも良いですが、今回は HTML5 か Chrome に関連する Talk を優先します。\u003cbr /\u003e\nLTの模様は東京側にも中継されます。 \u003cbr /\u003e\n\u003cbr /\u003e\u003cbr /\u003e\n\u003cb\u003e参加費:\u003c/b\u003e\u003cbr /\u003e\n　1000円\u003cbr /\u003e\n　※遅れての参加でも構いませんが、参加費は変わりません。\u003cbr /\u003e\n\u003cbr /\u003e\u003cbr /\u003e\n初めての試みなので、拙い部分もあると思いますが、よろしくお願いします。\u003cbr /\u003e\n\u003cbr /\u003e\u003cbr /\u003e\nなお、懇親会も行いたいと思います。\u003cbr /\u003e\n懇親会はこちらからお申し込みください。\u003cbr /\u003e\n\u003ca href=\"http://atnd.org/events/2293\"\u003ehttp://atnd.org/events/2293\u003c/a\u003e\u003cbr /\u003e\n\u003cbr /\u003e\n\u003cbr /\u003e\n\u003cb\u003eまた、参加される方で、Waveアカウントを持っていない方にはWaveアカウントに招待します。\u003c/b\u003e\u003c/p\u003e","event_url":"http://atnd.org/events/2294","started_at":"2009-12-09T19:00:00.000+09:00","ended_at":"2009-12-09T21:00:00.000+09:00","url":"http://www.sonic-city.or.jp/modules/access/","limit":33,"address":"埼玉県さいたま市大宮区桜木町1-7-5","place":"大宮ソニックシティ 5F 501会議室","lat":"35.9051733","lon":"139.6202295","owner_id":2471,"owner_nickname":"Akio Kondo(@kojira)","owner_twitter_id":"kojira","accepted":7,"waiting":0,"updated_at":"2009-11-26T14:54:24.000+09:00"}}]}