{"results_returned":1,"results_start":1,"events":[{"event":{"event_id":29786,"title":"BLOOD-C 見てきた","catch":"日記です","description":"\u003cp\u003eもともとこの企画、長編アニメ 2 本だったのが、 TV アニメ + 劇場版 2 本になって、 TV アニメがあまりに不評だったので TV アニメ + 劇場版 1 本になったと聞いている。\u003c/p\u003e\n\u003cp\u003e劇場版では明らかに劇場版 2 本分のキャラクターが詰め込まれていて、特に後半の展開はダッシュ気味だったし、消化不良の部分もあった。\u003c/p\u003e\n\u003cp\u003eそんなわけで尺が足りないせいかアクションシーンもさほど多くはないけど一つ一つの出来はよかった。\u003c/p\u003e\n\u003cp\u003eストーリは前述の通りかなり駆け足だったけど、やることはちゃんとやっていてそれなりの出来であったと思う。アクションシーン以外の演出もしっかりしていた。\u003c/p\u003e\n\u003cp\u003eエンドレスエイト茶番アニメの TV アニメと比較すると雲泥の出来で、金を払って見る価値はあるものだったと思う。\u003c/p\u003e\n\u003cp\u003eしかし返す返すも惜しいのは上映形態が何度も何度も変った事情が見ていても伺える点だ。あー劇場版 1 本目ではこいつとこいつがボスで 2 本目で文人が死ぬ予定だったのね〜みたいのが見てれば分かる。どうせ爆死なんだから無理矢理 2 本やってほしかった。\u003c/p\u003e","event_url":"http://atnd.org/events/29786","started_at":"2012-06-03T00:00:00.000+09:00","ended_at":null,"url":null,"limit":2147483647,"address":"","place":"","lat":null,"lon":null,"owner_id":3820,"owner_nickname":"ssig33","owner_twitter_id":null,"accepted":0,"waiting":0,"updated_at":"2012-06-03T22:23:19.000+09:00"}}]}