{"results_returned":1,"results_start":1,"events":[{"event":{"event_id":57505,"title":"関数型プログラミング入門編　②","catch":"～関数型プログラミングを知ろう！！","description":"\u003ch1\u003e関数プログラミング入門編\u003cbr /\u003e\n～関数型プログラミングを知ろう！！\u003c/h1\u003e\n\u003cp\u003e日時：11月12日（水）20：00～22：00（開場19：30、開始20：00）\u003c/p\u003e\n\u003cp\u003e場所：株式会社ファランクス　東京本社会議室\u003c/p\u003e\n\u003cp\u003e参加資格：何かしらのプログラミングに興味のある方\u003cbr /\u003e\n　　　　　もしくは実務経験のある方\u003c/p\u003e\n\u003cp\u003e参加費：無料\u003cbr /\u003e\n※プログラム終了後に簡単な懇親会を予定しております\u003c/p\u003e\n\u003ch2\u003eタイムテーブル\u003c/h2\u003e\n\u003ctable\u003e\n\t\u003ctr\u003e\n\t\t\u003cth\u003e時間\u003c/th\u003e\n\t\t\u003cth\u003eタイトル\u003c/th\u003e\n\t\u003c/tr\u003e\n\t\u003ctr\u003e\n\t\t\u003ctd\u003e20:00 \u0026#8211; 20:15\u003c/td\u003e\n\t\t\u003ctd\u003eオープニングトーク\u003c/td\u003e\n\t\u003c/tr\u003e\n\t\u003ctr\u003e\n\t\t\u003ctd\u003e20:15 \u0026#8211; 21:15\u003c/td\u003e\n\t\t\u003ctd\u003e勉強会スタート\u003c/td\u003e\n\t\u003c/tr\u003e\n\t\u003ctr\u003e\n\t\t\u003ctd\u003e21:15 \u0026#8211; 21:30\u003c/td\u003e\n\t\t\u003ctd\u003e質疑応答\u003c/td\u003e\n\t\u003c/tr\u003e\n\t\u003ctr\u003e\n\t\t\u003ctd\u003e21:30 \u0026#8211; 22:00\u003c/td\u003e\n\t\t\u003ctd\u003e懇親会\u003c/td\u003e\n\t\u003c/tr\u003e\n\u003c/table\u003e\n\u003ch2\u003e場所\u003c/h2\u003e\n\u003cp\u003e株式会社ファランクス　東京本社会議室\u003cbr /\u003e\n住所: 東京都新宿区西新宿6-24-1　西新宿三井ビル13F\u003c/p\u003e\n\u003ch2\u003e講演概要\u003c/h2\u003e\n\u003cp\u003e『関数型プログラミング入門編』\u003c/p\u003e\n\u003cp\u003e前回の振返りから初級編まで\u003cbr /\u003e\n・関数型プログラミングとは\u003c/p\u003e\n\u003cp\u003e※詳細は確定次第、アップします。\u003c/p\u003e","event_url":"http://atnd.org/events/57505","started_at":"2014-11-12T20:00:00.000+09:00","ended_at":"2014-11-12T22:00:00.000+09:00","url":"http://www.phalanx.co.jp/company/","limit":15,"address":"東京都新宿区西新宿6-24-1　西新宿三井ビル13F","place":"株式会社ファランクス本社（西新宿三井ビル13F）","lat":"35.6949733","lon":"139.6889837","owner_id":184187,"owner_nickname":"Akihisa Nakayama","owner_twitter_id":null,"accepted":9,"waiting":0,"updated_at":"2014-10-09T14:57:39.000+09:00"}}]}