{"results_returned":1,"results_start":1,"events":[{"event":{"event_id":67981,"title":"【DJクラブ風イベント♪】途中退場可能♪音楽に合わせてワイワイ交流","catch":null,"description":"\u003cp\u003e梅田からアクセス抜群♪♪\u003c/p\u003e\n\u003cp\u003e金曜日の夜をみんなで楽しみましょう(\u003cstrong\u003e≧∀≦\u003c/strong\u003e)\u003c/p\u003e\n\u003cp\u003eCLUBが苦手な人も安心です(^^)音も適度でワイワイ安心して交流出来ますよ♪\u003c/p\u003e\n\u003cp\u003eCLUBとスポーツバーのハイブリットな交流会です(^^)\u003c/p\u003e\n\u003cp\u003eこの日はDJイベントのため、男性はツードリンク付きで2000円、女性は入場無料です(\u003cstrong\u003e^^\u003c/strong\u003e)\u003c/p\u003e\n\u003cp\u003eみんなで乾杯しましょう♪♪\u003cbr /\u003e\n梅田からアクセス抜群♪♪\u003c/p\u003e\n\u003cp\u003e金曜日の夜をみんなで楽しみましょう(\u003cstrong\u003e≧∀≦\u003c/strong\u003e)\u003c/p\u003e\n\u003cp\u003eCLUBが苦手な人も安心です(^^)音も適度でワイワイ安心して交流出来ますよ♪\u003c/p\u003e\n\u003cp\u003eCLUBとスポーツバーのハイブリットな交流会です(^^)\u003c/p\u003e\n\u003cp\u003eこの日は腕前抜群のDJお二人が登場する貴重なイベント(\u003cstrong\u003e^^\u003c/strong\u003e)\u003c/p\u003e\n\u003cp\u003eみんなで乾杯しましょう♪♪\u003c/p\u003e\n\u003cp\u003eみんなが集まりやすい金曜日を楽しみましょう(\u003cstrong\u003e≧∀≦\u003c/strong\u003e\u003c/p\u003e\n\u003cp\u003eDJもたくさん活躍します(^^)\u003c/p\u003e\n\u003cp\u003eみんなが集まりやすい金曜日を楽しみましょう(\u003cstrong\u003e≧∀≦\u003c/strong\u003e)\u003c/p\u003e","event_url":"http://atnd.org/events/67981","started_at":"2015-07-03T22:00:00.000+09:00","ended_at":null,"url":"http://goo.gl/pMHB2n","limit":40,"address":"大阪市北区曾根崎1丁目7-13　レイソル曾根崎ビル5階","place":"大阪(梅田)","lat":"34.6994899","lon":"135.5026843","owner_id":210545,"owner_nickname":"[セイント]","owner_twitter_id":null,"accepted":0,"waiting":0,"updated_at":"2015-07-03T11:14:11.000+09:00"}}]}